pyss3/__init__.py
pyss3/cmd_line.py
pyss3/server.py
pyss3/util.py
pyss3/resources/evaluation_plot/angular-animate.min.js
pyss3/resources/evaluation_plot/angular.min.js
pyss3/resources/evaluation_plot/data.js
pyss3/resources/evaluation_plot/model_evaluation.html
pyss3/resources/evaluation_plot/plotly.min.js
pyss3/resources/live_test/favicon.ico
pyss3/resources/live_test/index.html
pyss3/resources/live_test/sb-blanco.png
pyss3/resources/live_test/unsl.png
pyss3/resources/live_test/css/bootstrap-theme.min.css
pyss3/resources/live_test/css/bootstrap.min.css
pyss3/resources/live_test/css/icon.css
pyss3/resources/live_test/css/materialize.css
pyss3/resources/live_test/css/materialize.min.css
pyss3/resources/live_test/fonts/cmu.css
pyss3/resources/live_test/fonts/cmunbx.woff
pyss3/resources/live_test/fonts/cmunrm.woff
pyss3/resources/live_test/fonts/cmunsl.woff
pyss3/resources/live_test/fonts/cmunti.woff
pyss3/resources/live_test/fonts/icon.woff2
pyss3/resources/live_test/js/angular-animate.min.js
pyss3/resources/live_test/js/angular.min.js
pyss3/resources/live_test/js/app.js
pyss3/resources/live_test/js/global.js
pyss3/resources/live_test/js/jquery-1.7.2.min.js
pyss3/resources/live_test/js/jquery-ui.min.js
pyss3/resources/live_test/js/materialize.min.js
pyss3-0.6.5.dist-info/licenses/LICENSE.txt
tests/__init__.py
tests/test_cmd_line.py
tests/test_pyss3.py
tests/test_server.py
tests/test_util.py
pyss3-0.6.5.dist-info/METADATA
pyss3-0.6.5.dist-info/WHEEL
pyss3-0.6.5.dist-info/entry_points.txt
pyss3-0.6.5.dist-info/top_level.txt
pyss3-0.6.5.dist-info/RECORD
