Metadata-Version: 2.4
Name: pyss3
Version: 0.6.5
Summary: Python package that implements the SS3 text classifier (with visualizations tools for XAI)
Home-page: https://github.com/sergioburdisso/pyss3
Maintainer: Sergio Burdisso
Maintainer-email: sergio.burdisso@gmail.com, sburdisso@unsl.edu.ar
License: MIT License
Classifier: Programming Language :: Python
Classifier: Programming Language :: Python :: 3
Classifier: Programming Language :: Python :: 3.5
Classifier: Programming Language :: Python :: 3.6
Classifier: Programming Language :: Python :: 3.7
Classifier: License :: OSI Approved :: MIT License
Classifier: Operating System :: OS Independent
Classifier: Intended Audience :: Science/Research
Classifier: Topic :: Scientific/Engineering
Classifier: Topic :: Scientific/Engineering :: Artificial Intelligence
Classifier: Topic :: Scientific/Engineering :: Visualization
Classifier: Operating System :: OS Independent
Requires-Python: >=2.7
License-File: LICENSE.txt
Requires-Dist: six
Requires-Dist: cython
Requires-Dist: scikit-learn[alldeps]>=0.20
Requires-Dist: tqdm>=4.8.4
Requires-Dist: matplotlib
Requires-Dist: iterative-stratification
Requires-Dist: stylecloud; python_version >= "3"
Dynamic: classifier
Dynamic: description
Dynamic: description-content-type
Dynamic: home-page
Dynamic: license
Dynamic: license-file
Dynamic: maintainer
Dynamic: maintainer-email
Dynamic: provides-extra
Dynamic: requires-dist
Dynamic: requires-python
Dynamic: summary
